Metadata-Version: 2.1
Name: odk-ppp
Version: 1.4.0
Summary: Converts XlsForms into readable formats.
Home-page: http://www.pma2020.org
Author: Joe Flack
Author-email: jflack@jhu.edu
License: LICENSE.txt
Platform: UNKNOWN
Requires-Dist: Jinja2 (>=2.9.6)
Requires-Dist: pmix (>=0.7.0)
